banana/__init__.py
banana/layout.py
banana/main.py
banana/assets/dashAgGridComponentFunctions.js
banana/assets/styles.css
banana/callbacks/__init__.py
banana/callbacks/_insert_row.py
banana/callbacks/_load_main_table.py
banana/callbacks/_load_side_menu.py
banana/callbacks/_open_history_modal.py
banana/callbacks/_open_insert_modal.py
banana/callbacks/_update_cell.py
banana/core/__init__.py
banana/core/errors.py
banana/core/history.py
banana/core/utils.py
banana/core/config/__init__.py
banana/core/config/compile.py
banana/core/config/models.py
banana/core/tables/__init__.py
banana/core/tables/compile.py
banana/core/tables/models.py
banana/queries/__init__.py
banana/queries/_check_duplicated_values.py
banana/queries/_create_foreign_key_options.py
banana/queries/_delete_row.py
banana/queries/_execute_query.py
banana/queries/_get_primary_key.py
banana/queries/_insert_row.py
banana/queries/_select_table.py
banana/queries/_update_cell.py
banana_manager-0.6.1.dist-info/LICENSE
banana_manager-0.6.1.dist-info/METADATA
banana_manager-0.6.1.dist-info/WHEEL
banana_manager-0.6.1.dist-info/top_level.txt
banana_manager-0.6.1.dist-info/RECORD
