Metadata-Version: 2.1
Name: banana-manager
Version: 0.6.1
Summary: Ready-to-go web app for end-users to interact with tables in a database.
Home-page: https://github.com/GusFurtado/BananaManager
Author: Gustavo Furtado
Author-email: gustavofurtado2@gmail.com
License: MIT
License-File: LICENSE
Requires-Dist: dash-ag-grid
Requires-Dist: dash-iconify
Requires-Dist: dash-mantine-components
Requires-Dist: pydantic
Requires-Dist: pyyaml
Requires-Dist: Flask-SQLAlchemy
